{"AboutText":{"id":"AboutText","value":"Copyright &copy; {0} Infor. Alle rettigheder forbeholdes. Ord- og designmærkerne anført heri er varemærker og/eller registrerede varemærker tilhørende Infor og/eller dennes affilierede selskaber og datterselskaber. Alle andre varemærker angivet heri tilhører de respektive ejere."},"Actions":{"id":"Actions","value":"Handlinger"},"Add":{"id":"Add","value":"Tilføj"},"AddComments":{"id":"AddComments","value":"Tilføj kommentarer"},"AddNewTab":{"id":"AddNewTab","value":"Tilføj ny fane"},"AdministrativeLeave":{"id":"AdministrativeLeave","value":"Administrativ orlov"},"AdvancedFilter":{"id":"AdvancedFilter","value":"Opret avanceret filter"},"Afrikaans":{"id":"Afrikaans","value":"Afrikaans"},"Alabaster":{"id":"Alabaster","value":"Alabaster"},"Alert":{"id":"Alert","value":"Advarsel"},"AlertOnPage":{"id":"AlertOnPage","value":"Advarselsmeddelelse(r) på side"},"AlignCenterHorizontally":{"id":"AlignCenterHorizontally","value":"Centrer vandret"},"AligntoBottom":{"id":"AligntoBottom","value":"Juster bund"},"All":{"id":"All","value":"Alle"},"AllDay":{"id":"AllDay","value":"Hele dagen"},"AllResults":{"id":"AllResults","value":"Alle resultater for"},"Amber":{"id":"Amber","value":"Gul"},"Amethyst":{"id":"Amethyst","value":"Ametyst"},"And":{"id":"And","value":"og"},"AppMenuTriggerText":{"id":"AppMenuTriggerText","value":"Menu"},"AppMenuTriggerTextAlt":{"id":"AppMenuTriggerTextAlt","value":"Udløser for Programmenu"},"Apply":{"id":"Apply","value":"Anvend"},"Arabic":{"id":"Arabic","value":"Arabisk"},"AreaChart":{"id":"AreaChart","value":"Områdediagram"},"Attach":{"id":"Attach","value":"Vedhæft"},"Available":{"id":"Available","value":"Tilgængelige"},"Azure":{"id":"Azure","value":"Azurblå"},"BackgroundColor":{"id":"BackgroundColor","value":"Baggrundsfarve"},"BarChart":{"id":"BarChart","value":"Søjlediagram"},"Between":{"id":"Between","value":"Mellem"},"BillionsAbbrev":{"id":"BillionsAbbrev","value":"{0}b"},"Blockquote":{"id":"Blockquote","value":"Bloktilbud"},"Bold":{"id":"Bold","value":"Fed"},"BookmarkThis":{"id":"BookmarkThis","value":"Bogmærk dette"},"Bookmarked":{"id":"Bookmarked","value":"Bogmærke oprettet"},"Breadcrumb":{"id":"Breadcrumb","value":"Brødkrumme"},"Browser":{"id":"Browser","value":"Browser"},"BrowserLanguage":{"id":"BrowserLanguage","value":"Browsersprog"},"Bulgarian":{"id":"Bulgarian","value":"Bulgarsk"},"BulletedList":{"id":"BulletedList","value":"Punktopstilling"},"Calendar":{"id":"Calendar","value":"Kalender"},"Camera":{"id":"Camera","value":"Kamera"},"Cancel":{"id":"Cancel","value":"Annuller"},"CapsLockOn":{"id":"CapsLockOn","value":"Caps Lock til"},"Cart":{"id":"Cart","value":"Vogn"},"CenterText":{"id":"CenterText","value":"Centrer"},"ChangeSelection":{"id":"ChangeSelection","value":"Brug piletasterne til at ændre det valgte element."},"ChangeView":{"id":"ChangeView","value":"Skift visning"},"CharactersLeft":{"id":"CharactersLeft","value":"Tegn tilbage {0}"},"CharactersMax":{"id":"CharactersMax","value":"Maks. antal tegn "},"Checkbox":{"id":"Checkbox","value":"Afkrydsningsfelt"},"Checked":{"id":"Checked","value":"Kontrolleret"},"Chinese":{"id":"Chinese","value":"Kinesisk"},"ChooseFont":{"id":"ChooseFont","value":"Vælg typografi"},"Classic":{"id":"Classic","value":"Klassisk"},"ClassicDarkTheme":{"id":"ClassicDarkTheme","value":"Klassisk Mørk"},"ClassicHighContrastTheme":{"id":"ClassicHighContrastTheme","value":"Klassisk Høj kontrast"},"ClassicLightTheme":{"id":"ClassicLightTheme","value":"Klassisk Lys"},"Clear":{"id":"Clear","value":"Ryd"},"ClearFilter":{"id":"ClearFilter","value":"Ryd filter"},"ClearFormatting":{"id":"ClearFormatting","value":"Ryd formatering"},"ClearSelection":{"id":"ClearSelection","value":"(Ryd markering)"},"Clickable":{"id":"Clickable","value":"Klikbar i editor"},"Clock":{"id":"Clock","value":"Ur"},"Close":{"id":"Close","value":"Luk"},"Collapse":{"id":"Collapse","value":"Skjul"},"CollapseAppTray":{"id":"CollapseAppTray","value":"Skjul app-bakke"},"Color":{"id":"Color","value":"Farve"},"ColorPickerSelection":{"id":"ColorPickerSelection","value":"Vælg en brugerdefineret farve"},"ColorPickerTriggerButton":{"id":"ColorPickerTriggerButton","value":"Klik for at åbne farvevælgeren"},"Colors":{"id":"Colors","value":"Farver"},"Columns":{"id":"Columns","value":"Kolonner"},"Comments":{"id":"Comments","value":"Kommentarer"},"CompanyHoliday":{"id":"CompanyHoliday","value":"Firmaferie"},"Completed":{"id":"Completed","value":"Fuldført"},"Component":{"id":"Component","value":"Komponent"},"Compose":{"id":"Compose","value":"Opret"},"Confirm":{"id":"Confirm","value":"Bekræft"},"ConfirmOnPage":{"id":"ConfirmOnPage","value":"Bekræftelsesmeddelelse(r) på side"},"Contains":{"id":"Contains","value":"Indeholder"},"Contrast":{"id":"Contrast","value":"Kontrast"},"CookiesEnabled":{"id":"CookiesEnabled","value":"Cookies aktiveret"},"Copy":{"id":"Copy","value":"Kopiér"},"Croatian":{"id":"Croatian","value":"Kroatisk"},"CssClass":{"id":"CssClass","value":"Css-klasse"},"Cut":{"id":"Cut","value":"Klip"},"Czech":{"id":"Czech","value":"Tjekkisk"},"Danish":{"id":"Danish","value":"Dansk"},"Dark":{"id":"Dark","value":"Mørk"},"Datagrid":{"id":"Datagrid","value":"Datagitter"},"Date":{"id":"Date","value":"Dato"},"DatePickerTriggerButton":{"id":"DatePickerTriggerButton","value":"Udløser for datovælger"},"Day":{"id":"Day","value":"Dag"},"DayAbbreviatedFri":{"id":"DayAbbreviatedFri","value":"Fre"},"DayAbbreviatedMon":{"id":"DayAbbreviatedMon","value":"Man"},"DayAbbreviatedSat":{"id":"DayAbbreviatedSat","value":"Lør"},"DayAbbreviatedSun":{"id":"DayAbbreviatedSun","value":"Søn"},"DayAbbreviatedThu":{"id":"DayAbbreviatedThu","value":"Tor"},"DayAbbreviatedTue":{"id":"DayAbbreviatedTue","value":"Tir"},"DayAbbreviatedWed":{"id":"DayAbbreviatedWed","value":"Ons"},"DayNarrowFri":{"id":"DayNarrowFri","value":"F"},"DayNarrowMon":{"id":"DayNarrowMon","value":"M"},"DayNarrowSat":{"id":"DayNarrowSat","value":"L"},"DayNarrowSun":{"id":"DayNarrowSun","value":"S"},"DayNarrowThu":{"id":"DayNarrowThu","value":"T"},"DayNarrowTue":{"id":"DayNarrowTue","value":"T"},"DayNarrowWed":{"id":"DayNarrowWed","value":"O"},"DayPeriod0":{"id":"DayPeriod0","value":"AM"},"DayPeriod1":{"id":"DayPeriod1","value":"PM"},"DayWideFri":{"id":"DayWideFri","value":"Fredag"},"DayWideMon":{"id":"DayWideMon","value":"Mandag"},"DayWideSat":{"id":"DayWideSat","value":"Lørdag"},"DayWideSun":{"id":"DayWideSun","value":"Søndag"},"DayWideThu":{"id":"DayWideThu","value":"Torsdag"},"DayWideTue":{"id":"DayWideTue","value":"Tirsdag"},"DayWideWed":{"id":"DayWideWed","value":"Onsdag"},"Days":{"id":"Days","value":"Dage "},"DaysOverdue":{"id":"DaysOverdue","value":"{0} dage overskredet"},"DaysRemaining":{"id":"DaysRemaining","value":"{0} dage tilbage"},"Default":{"id":"Default","value":"Standard"},"Delete":{"id":"Delete","value":"Slet"},"DeleteEvent":{"id":"DeleteEvent","value":"Slet begivenhed"},"Device":{"id":"Device","value":"Enhed"},"Dirty":{"id":"Dirty","value":"Række er ændret"},"DiscretionaryTimeOff":{"id":"DiscretionaryTimeOff","value":"Ekstra fri"},"DistributeHoriz":{"id":"DistributeHoriz","value":"Distribuer horisontalt"},"Document":{"id":"Document","value":"Dokument"},"DoesNotContain":{"id":"DoesNotContain","value":"Indeholder ikke"},"DoesNotEndWith":{"id":"DoesNotEndWith","value":"Slutter ikke med"},"DoesNotEqual":{"id":"DoesNotEqual","value":"Er ikke lig med"},"DoesNotStartWith":{"id":"DoesNotStartWith","value":"Starter ikke med"},"Down":{"id":"Down","value":"Ned"},"Download":{"id":"Download","value":"Hent"},"Drilldown":{"id":"Drilldown","value":"Detaljefokus"},"Drillup":{"id":"Drillup","value":"Analysér op"},"Dropdown":{"id":"Dropdown","value":"Rulleliste"},"DropdownTriggerButton":{"id":"DropdownTriggerButton","value":"Klik for at åbne rullelisten"},"Duplicate":{"id":"Duplicate","value":"Dupliker"},"Duration":{"id":"Duration","value":"Varighed"},"Dutch":{"id":"Dutch","value":"Hollandsk"},"EarlyOrEquals":{"id":"EarlyOrEquals","value":"Tidligere end eller lig med"},"EarlyOrUntil":{"id":"EarlyOrUntil","value":"Tidligere end eller indtil den"},"EarlyThan":{"id":"EarlyThan","value":"Tidligere end"},"Edit":{"id":"Edit","value":"Rediger"},"EitherSelectedOrNotSelected":{"id":"EitherSelectedOrNotSelected","value":"Enten valgt eller ikke valgt"},"EmailValidation":{"id":"EmailValidation","value":"E-mailadresse ikke gyldig"},"Emerald":{"id":"Emerald","value":"Smaragd"},"EndsWith":{"id":"EndsWith","value":"Slutter med"},"English":{"id":"English","value":"Engelsk (USA)"},"EnterComments":{"id":"EnterComments","value":"Indtast kommentarer her..."},"Equals":{"id":"Equals","value":"Lig med"},"Error":{"id":"Error","value":"Fejl"},"ErrorAllowedTypes":{"id":"ErrorAllowedTypes","value":"Filtypen er ikke tilladt"},"ErrorMaxFileSize":{"id":"ErrorMaxFileSize","value":"Overskred grænse på filstørrelse"},"ErrorMaxFiles":{"id":"ErrorMaxFiles","value":"Der kan ikke uploades mere end det maksimale antal filer ({n})."},"ErrorMaxFilesInProcess":{"id":"ErrorMaxFilesInProcess","value":"Overskred tilladt grænse for højeste antal filer"},"ErrorOnPage":{"id":"ErrorOnPage","value":"Fejlmeddelelse(r) på side"},"Estonian":{"id":"Estonian","value":"Estisk"},"Event":{"id":"Event","value":"Begivenhed"},"EventType":{"id":"EventType","value":"Begivenhedstype"},"ExampleData":{"id":"ExampleData","value":"Eksempeldata"},"ExampleLabel":{"id":"ExampleLabel","value":"Eksempeletiket"},"ExamplePlaceholder":{"id":"ExamplePlaceholder","value":"Eksempelpladsholder"},"ExitFullView":{"id":"ExitFullView","value":"Afslut fuld visning"},"Expand":{"id":"Expand","value":"Udvid"},"ExpandAppTray":{"id":"ExpandAppTray","value":"Udvid app-bakke"},"ExpandCollapse":{"id":"ExpandCollapse","value":"Udvid / Skjul"},"Export":{"id":"Export","value":"Eksportér"},"ExportAsSpreadsheet":{"id":"ExportAsSpreadsheet","value":"Eksporter som regneark"},"ExportToCsv":{"id":"ExportToCsv","value":"Eksportér til CSV"},"ExportToExcel":{"id":"ExportToExcel","value":"Eksportér til Excel"},"ExtraSmall":{"id":"ExtraSmall","value":"Ekstra lille"},"Favorite":{"id":"Favorite","value":"Foretrukken"},"FieldFilter":{"id":"FieldFilter","value":"Feltfilter"},"FileUpload":{"id":"FileUpload","value":"Filoverførsel. Tryk på Enter for at navigere til en fil"},"Filter":{"id":"Filter","value":"Filter"},"Finnish":{"id":"Finnish","value":"Finsk"},"FirstPage":{"id":"FirstPage","value":"Første side"},"Folder":{"id":"Folder","value":"Mappe"},"FontPickerHeader":{"id":"FontPickerHeader","value":"Sidehoved {0}"},"FontPickerNormal":{"id":"FontPickerNormal","value":"Normal tekst"},"FontPickerStyle":{"id":"FontPickerStyle","value":"Typografi"},"Forms":{"id":"Forms","value":"Formularer"},"French":{"id":"French","value":"Fransk"},"From":{"id":"From","value":"Fra"},"FullView":{"id":"FullView","value":"Fuld visning"},"German":{"id":"German","value":"Tysk"},"Go":{"id":"Go","value":"Gå til"},"GoBack":{"id":"GoBack","value":"Gå tilbage"},"GoDown":{"id":"GoDown","value":"Gå ned"},"GoForward":{"id":"GoForward","value":"Gå frem"},"GoUp":{"id":"GoUp","value":"Gå op"},"Graphite":{"id":"Graphite","value":"Grafit"},"GreaterOrEquals":{"id":"GreaterOrEquals","value":"Større end eller lig med"},"GreaterThan":{"id":"GreaterThan","value":"Større end"},"Grid":{"id":"Grid","value":"Gitter"},"Group":{"id":"Group","value":"Gruppe"},"Groups":{"id":"Groups","value":"Grupper"},"GroupsPerPage":{"id":"GroupsPerPage","value":"{0} Grupper pr. side"},"HeadingFour":{"id":"HeadingFour","value":"Overskrift fire"},"HeadingThree":{"id":"HeadingThree","value":"Overskrift tre"},"Hebrew":{"id":"Hebrew","value":"Hebraisk"},"Hide":{"id":"Hide","value":"Skjul"},"HighContrast":{"id":"HighContrast","value":"Høj kontrast"},"Highest":{"id":"Highest","value":"Højeste"},"Highlight":{"id":"Highlight","value":"Fremhæv"},"Hindi":{"id":"Hindi","value":"Hindi"},"Home":{"id":"Home","value":"Start"},"Hour":{"id":"Hour","value":"Time"},"Hours":{"id":"Hours","value":"Timer"},"HtmlView":{"id":"HtmlView","value":"Html-visning"},"Hungarian":{"id":"Hungarian","value":"Ungarsk"},"Id":{"id":"Id","value":"Id"},"Image":{"id":"Image","value":"Billede"},"Import":{"id":"Import","value":"Importér"},"InProgress":{"id":"In Progress","value":"I gang"},"InRange":{"id":"InRange","value":"Inden for interval"},"Indonesian":{"id":"Indonesian","value":"Indonesisk"},"Info":{"id":"Info","value":"Info"},"InfoOnPage":{"id":"InfoOnPage","value":"Informationsmeddelelse(r) på side"},"Insert":{"id":"Insert","value":"Indsæt"},"InsertAnchor":{"id":"InsertAnchor","value":"Indsæt anker"},"InsertHyperlink":{"id":"InsertHyperlink","value":"Indsæt hyperlink"},"InsertImage":{"id":"InsertImage","value":"Indsæt billede"},"InsertLink":{"id":"InsertLink","value":"Indsæt link"},"InsertUrl":{"id":"InsertUrl","value":"Indsæt Url"},"InvalidDate":{"id":"InvalidDate","value":"Ugyldig dato"},"InvalidDateTime":{"id":"InvalidDateTime","value":"Ugyldig dato eller tid"},"InvalidTime":{"id":"InvalidTime","value":"Ugyldig tid"},"Inventory":{"id":"Inventory","value":"Lager"},"IsEmpty":{"id":"IsEmpty","value":"Er tom"},"IsNotEmpty":{"id":"IsNotEmpty","value":"Er ikke tom"},"Italic":{"id":"Italic","value":"Kursiv"},"ItemsSelected":{"id":"ItemsSelected","value":"Valgte elementer"},"Japanese":{"id":"Japanese","value":"Japansk"},"JustifyCenter":{"id":"JustifyCenter","value":"Centrer"},"JustifyLeft":{"id":"JustifyLeft","value":"Venstrejusteret"},"JustifyRight":{"id":"JustifyRight","value":"Højrejusteret"},"Keyword":{"id":"Keyword","value":"Nøgleord"},"Korean":{"id":"Korean","value":"Koreansk"},"Language":{"id":"Language","value":"Sprog"},"Large":{"id":"Large","value":"Stor"},"LastPage":{"id":"LastPage","value":"Sidste side"},"LaterOrEquals":{"id":"LaterOrEquals","value":"Senere end eller lig med"},"LaterOrOn":{"id":"LaterOrOn","value":"Senere end eller den"},"LaterThan":{"id":"LaterThan","value":"Senere end"},"Latvian":{"id":"Latvian","value":"Lettisk"},"Launch":{"id":"Launch","value":"Start"},"Left":{"id":"Left","value":"Venstre"},"Legend":{"id":"Legend","value":"Forklaring"},"LessOrEquals":{"id":"LessOrEquals","value":"Mindre end eller lig med"},"LessThan":{"id":"LessThan","value":"Mindre end"},"Light":{"id":"Light","value":"Lys"},"Link":{"id":"Link","value":"Link"},"LineChart":{"id":"LineChart","value":"Kurvediagram"},"Lithuanian":{"id":"Lithuanian","value":"Litauisk"},"Load":{"id":"Load","value":"Indlæs"},"Loading":{"id":"Loading","value":"Indlæser"},"Locale":{"id":"Locale","value":"Landestandard"},"Locked":{"id":"Locked","value":"Låst"},"Logout":{"id":"Logout","value":"Log af"},"Lookup":{"id":"Lookup","value":"Slå op"},"LookupTriggerButton":{"id":"LookupTriggerButton","value":"Udløser for opslag"},"Lowest":{"id":"Lowest","value":"Lavest"},"Mail":{"id":"Mail","value":"E-mail"},"Malay":{"id":"Malay","value":"Malaysisk"},"MapPin":{"id":"MapPin","value":"Nål"},"Maximize":{"id":"Maximize","value":"Maksimer"},"Median":{"id":"Median","value":"Median"},"Medium":{"id":"Medium","value":"Mellem"},"Menu":{"id":"Menu","value":"Menu"},"MenuGroup":{"id":"MenuGroup","value":"Menugruppen indeholder {0} element(er)"},"MillionsAbbrev":{"id":"MillionsAbbrev","value":"{0}M"},"MingleShare":{"id":"MingleShare","value":"Del med Ming.le"},"Minimize":{"id":"Minimize","value":"Minimer"},"Minus":{"id":"Minus","value":"Minus"},"Minute":{"id":"Minute","value":"Minut"},"Minutes":{"id":"Minutes","value":"Minutter"},"Mobile":{"id":"Mobile","value":"Mobil"},"Mode":{"id":"Mode","value":"Tilstand"},"Modes":{"id":"Modes","value":"Tilstande"},"Month":{"id":"Month","value":"Måned"},"MonthAbbreviatedApr":{"id":"MonthAbbreviatedApr","value":"Apr"},"MonthAbbreviatedAug":{"id":"MonthAbbreviatedAug","value":"Aug"},"MonthAbbreviatedDec":{"id":"MonthAbbreviatedDec","value":"Dec"},"MonthAbbreviatedFeb":{"id":"MonthAbbreviatedFeb","value":"Feb"},"MonthAbbreviatedJan":{"id":"MonthAbbreviatedJan","value":"Jan"},"MonthAbbreviatedJuly":{"id":"MonthAbbreviatedJuly","value":"Jul"},"MonthAbbreviatedJune":{"id":"MonthAbbreviatedJune","value":"Jun"},"MonthAbbreviatedLowerCaseApr":{"id":"MonthAbbreviatedApr","value":"Apr"},"MonthAbbreviatedLowerCaseDec":{"id":"MonthAbbreviatedDec","value":"Dec"},"MonthAbbreviatedLowerCaseFeb":{"id":"MonthAbbreviatedFeb","value":"Feb"},"MonthAbbreviatedLowerCaseJan":{"id":"MonthAbbreviatedJan","value":"Jan"},"MonthAbbreviatedLowerCaseJuly":{"id":"MonthAbbreviatedJuly","value":"Jul"},"MonthAbbreviatedLowerCaseJune":{"id":"MonthAbbreviatedJune","value":"Jun"},"MonthAbbreviatedLowerCaseLowerCaseAug":{"id":"MonthAbbreviatedAug","value":"Aug"},"MonthAbbreviatedLowerCaseMar":{"id":"MonthAbbreviatedMar","value":"Mar"},"MonthAbbreviatedLowerCaseMay":{"id":"MonthAbbreviatedMay","value":"Maj"},"MonthAbbreviatedLowerCaseNov":{"id":"MonthAbbreviatedNov","value":"Nov"},"MonthAbbreviatedLowerCaseOct":{"id":"MonthAbbreviatedOct","value":"Okt"},"MonthAbbreviatedLowerCaseSep":{"id":"MonthAbbreviatedSep","value":"Sep"},"MonthAbbreviatedMar":{"id":"MonthAbbreviatedMar","value":"Mar"},"MonthAbbreviatedMay":{"id":"MonthAbbreviatedMay","value":"Maj"},"MonthAbbreviatedNov":{"id":"MonthAbbreviatedNov","value":"Nov"},"MonthAbbreviatedOct":{"id":"MonthAbbreviatedOct","value":"Okt"},"MonthAbbreviatedSep":{"id":"MonthAbbreviatedSep","value":"Sep"},"MonthWideApr":{"id":"MonthWideApr","value":"April"},"MonthWideAug":{"id":"MonthWideAug","value":"August"},"MonthWideDec":{"id":"MonthWideDec","value":"December"},"MonthWideFeb":{"id":"MonthWideFeb","value":"Februar"},"MonthWideJan":{"id":"MonthWideJan","value":"Januar"},"MonthWideJuly":{"id":"MonthWideJuly","value":"Juli"},"MonthWideJune":{"id":"MonthWideJune","value":"Juni"},"MonthWideLowerCaseApr":{"id":"MonthWideApr","value":"april"},"MonthWideLowerCaseAug":{"id":"MonthWideAug","value":"august"},"MonthWideLowerCaseDec":{"id":"MonthWideDec","value":"december"},"MonthWideLowerCaseFeb":{"id":"MonthWideFeb","value":"februar"},"MonthWideLowerCaseJan":{"id":"MonthWideJan","value":"januar"},"MonthWideLowerCaseJuly":{"id":"MonthWideJuly","value":"juli"},"MonthWideLowerCaseJune":{"id":"MonthWideJune","value":"juni"},"MonthWideLowerCaseMar":{"id":"MonthWideMar","value":"marts"},"MonthWideLowerCaseMay":{"id":"MonthWideMay","value":"maj"},"MonthWideLowerCaseNov":{"id":"MonthWideNov","value":"november"},"MonthWideLowerCaseOct":{"id":"MonthWideOct","value":"oktober"},"MonthWideLowerCaseSep":{"id":"MonthWideSep","value":"september"},"MonthWideMar":{"id":"MonthWideMar","value":"Marts"},"MonthWideMay":{"id":"MonthWideMay","value":"Maj"},"MonthWideNov":{"id":"MonthWideNov","value":"November"},"MonthWideOct":{"id":"MonthWideOct","value":"Oktober"},"MonthWideSep":{"id":"MonthWideSep","value":"September"},"More":{"id":"More","value":"Mere"},"MoreActions":{"id":"MoreActions","value":"Flere handlinger"},"MoveToLeft":{"id":"MoveToLeft","value":"Flyt til venstre"},"MoveToRight":{"id":"MoveToRight","value":"Flyt til højre"},"MsgDirty":{"id":"MsgDirty","value":", Ændret"},"New":{"id":"New","value":"Ny"},"NewDarkTheme":{"id":"NewDarkTheme","value":"Ny Mørk"},"NewDocument":{"id":"NewDocument","value":"Nyt dokument"},"NewEvent":{"id":"NewEvent","value":"Ny begivenhed"},"NewEventDetails":{"id":"NewEventDetails","value":"Detaljer for ny begivenhed"},"NewHighContrastTheme":{"id":"NewHighContrastTheme","value":"Ny Høj kontrast"},"NewItem":{"id":"NewItem","value":"Nyt element"},"NewLightTheme":{"id":"NewLightTheme","value":"Ny Lys"},"NewRow":{"id":"New","value":"Ny"},"NewWindow":{"id":"NewWindow","value":"Nyt vindue"},"Next":{"id":"Next","value":"Næste"},"NextMonth":{"id":"NextMonth","value":"Næste måned"},"NextPage":{"id":"NextPage","value":"Næste side"},"NextRecord":{"id":"NextRecord","value":"Næste post"},"NextWeek":{"id":"NextWeek","value":"Næste uge"},"NextYear":{"id":"NextYear","value":"Næste år"},"No":{"id":"No","value":"Nej"},"NoCommentsEntered":{"id":"NoCommentsEntered","value":"Der er ikke angivet nogen kommentarer"},"NoData":{"id":"NoData","value":"Ingen tilgængelige data"},"NoDataFilter":{"id":"NoDataFilter","value":"Ingen tilgængelige data. Lav en ny filtersøgning for at se flere resultater."},"NoDataList":{"id":"NoDataList","value":"Ingen tilgængelige data. Vælg fra ovenstående liste for at se flere resultater."},"NoResults":{"id":"NoResults","value":"Ingen resultater"},"NoRecordSelected":{"id":"NoRecordSelected","value":"0 poster er valgt"},"NoTitle":{"id":"NoTitle","value":"(Ingen titel)"},"None":{"id":"None","value":"Ingen"},"Normal":{"id":"Normal","value":"Normal"},"Norwegian":{"id":"Norwegian","value":"Norsk"},"NotSelected":{"id":"NotSelected","value":"Ikke valgt"},"Notes":{"id":"Notes","value":"Noter"},"NumberList":{"id":"NumberList","value":"Nummerliste"},"Ok":{"id":"Ok","value":"OK"},"OpenBackClose":{"id":"OpenBackClose","value":"Åbn / Tilbage / Luk"},"OpenClose":{"id":"OpenClose","value":"Åbn / Luk"},"OperatingSystem":{"id":"OperatingSystem","value":"Operativsystem"},"OrderedList":{"id":"OrderedList","value":"Indsæt/Fjern punktopstilling med tal"},"Page":{"id":"Page","value":"side "},"PageOf":{"id":"PageOf","value":"Side {0} af {1}"},"PageOn":{"id":"PageOn","value":"Du er i øjeblikket på side "},"Pagination":{"id":"Pagination","value":"Sideangivelse"},"PaidTimeOff":{"id":"PaidTimeOff","value":"Betalt fri"},"PasswordConfirmValidation":{"id":"PasswordConfirmValidation","value":"Adgangskode skal være den samme"},"PasswordValidation":{"id":"PasswordValidation","value":"<strong>Adgangskode skal</strong><br>Bestå af mindst 10 tegn<br>Indeholde mindst ét stort bogstav<br>Indeholde mindst ét lille bogstav<br>Indeholde ét specialtegn<br>Ikke indeholde dit brugernavn<br>Ikke være en tidligere anvendt adgangskode<br>"},"Paste":{"id":"Paste","value":"Sæt ind"},"Peak":{"id":"Peak","value":"Spids"},"Pending":{"id":"Pending","value":"Afventer"},"Period":{"id":"Period","value":"Periode"},"Personalization":{"id":"Personalization","value":"Brugertilpasning"},"PersonalizeColumns":{"id":"PersonalizeColumns","value":"Tilpas kolonner"},"Plan":{"id":"Plan","value":"Plan"},"Platform":{"id":"Platform","value":"Platform"},"Polish":{"id":"Polish","value":"Polsk"},"Portuguese":{"id":"Portuguese","value":"Portugisisk"},"PressDown":{"id":"PressDown","value":"Tryk på pil ned for at vælge"},"PressShiftF10":{"id":"PressShiftF10","value":"Tryk på Skift+F10 for at åbne genvejsmenuen."},"Previous":{"id":"Previous","value":"Forrige"},"PreviousMonth":{"id":"PreviousMonth","value":"Forrige måned"},"PreviousPage":{"id":"PreviousPage","value":"Forrige side"},"PreviousRecord":{"id":"PreviousRecord","value":"Forrige post"},"PreviousWeek":{"id":"PreviousWeek","value":"Forrige uge"},"PreviousYear":{"id":"PreviousYear","value":"Forrige år"},"Print":{"id":"Print","value":"Udskriv"},"Range":{"id":"Range","value":"Område"},"RecordsPerPage":{"id":"RecordsPerPage","value":"{0} poster pr. side"},"RecordsPerPageNoToken":{"id":"RecordsPerPageNoToken","value":"Poster pr. side"},"RecordSelected":{"id":"RecordSelected","value":"{0} post er valgt"},"RecordsSelected":{"id":"RecordsSelected","value":"{0} poster er valgt"},"Redo":{"id":"Redo","value":"Annuller fortryd"},"Refresh":{"id":"Refresh","value":"Opdater"},"ReorderRows":{"id":"ReorderRows","value":"Lav om på rækkernes rækkefølge"},"RequestTimeOff":{"id":"RequestTimeOff","value":"Anmod om fri"},"Required":{"id":"Required","value":"Obligatorisk"},"Reset":{"id":"Reset","value":"Nulstil"},"ResetDefault":{"id":"ResetDefault","value":"Gendan til standard"},"Result":{"id":"Result","value":"({0} resultat)"},"ResultOf":{"id":"ResultOf","value":"{0} af {1} resultat"},"Results":{"id":"Results","value":"({0} resultater)"},"ResultsOf":{"id":"ResultsOf","value":"{0} af {1} resultater"},"Right":{"id":"Right","value":"Højre"},"RightAlign":{"id":"RightAlign","value":"Højrejusteret"},"RightAlignText":{"id":"RightAlignText","value":"Højrejusteret"},"Roles":{"id":"Roles","value":"Roller"},"Romanian":{"id":"Romanian","value":"Rumænsk"},"RowHeight":{"id":"RowHeight","value":"Rækkehøjde"},"Ruby":{"id":"Ruby","value":"Rubinrød"},"RunFilter":{"id":"RunFilter","value":"Kør filter"},"Russian":{"id":"Russian","value":"Russisk"},"SameWindow":{"id":"SameWindow","value":"Samme vindue"},"Save":{"id":"Save","value":"Gem"},"SaveCurrentView":{"id":"SaveCurrentView","value":"Gem aktuel visning"},"SavedViews":{"id":"SavedViews","value":"Gemte visninger"},"Schedule":{"id":"Schedule","value":"Plan"},"Search":{"id":"Search","value":"Søg"},"SearchColumnName":{"id":"SearchColumnName","value":"Søg efter et kolonnenavn"},"SearchFolder":{"id":"SearchFolder","value":"Søg i mappe"},"SearchList":{"id":"SearchList","value":"Søgeliste"},"Second":{"id":"Second","value":"Sekund"},"Seconds":{"id":"Seconds","value":"Sekunder"},"Select":{"id":"Select","value":"Vælg"},"SelectAll":{"id":"SelectAll","value":"Vælg alt"},"SelectDay":{"id":"SelectDay","value":"Vælg en dag"},"Selected":{"id":"Selected","value":"Valgt"},"SelectedOptions":{"id":"SelectedOptions","value":"Valgte muligheder"},"Selection":{"id":"Selection","value":"Valg"},"Send":{"id":"Send","value":"Send"},"SetTime":{"id":"SetTime","value":"Indstil tid"},"Settings":{"id":"Settings","value":"Indstillinger"},"Short":{"id":"Short","value":"Kort"},"Show":{"id":"Show","value":"Vis"},"ShowEvent":{"id":"ShowEvent","value":"Vis begivenhed"},"ShowFilterRow":{"id":"ShowFilterRow","value":"Vis filterrække"},"ShowLess":{"id":"ShowLess","value":"Vis mindre"},"ShowMore":{"id":"ShowMore","value":"Vis mere"},"SickTime":{"id":"SickTime","value":"Sygedag"},"SkipToMain":{"id":"SkipToMain","value":"Spring til hovedindhold"},"Slate":{"id":"Slate","value":"Skifergrå"},"SlideOf":{"id":"SlideOf","value":"Slide {0} af {1}"},"SliderHandle":{"id":"SliderHandle","value":"Håndtag til"},"SliderMaximumHandle":{"id":"SliderMaximumHandle","value":"Maks. områdehåndtag til"},"SliderMinimumHandle":{"id":"SliderMinimumHandle","value":"Min. områdehåndtag til"},"SlidesOf":{"id":"SlidesOf","value":"Slide {0} og {1} af {2}"},"Slovak":{"id":"Slovak","value":"Slovakisk"},"Slovenian":{"id":"Slovenian","value":"Slovensk"},"Small":{"id":"Small","value":"Lille"},"SohoDarkTheme":{"id":"SohoDarkTheme","value":"Soho Mørk"},"SohoHighContrastTheme":{"id":"SohoHighContrastTheme","value":"Soho Høj kontrast"},"SohoLightTheme":{"id":"SohoLightTheme","value":"Soho Lys"},"SortAtoZ":{"id":"SortAtoZ","value":"Sortér stigende"},"SortDown":{"id":"SortDown","value":"Sortér ned"},"SortUp":{"id":"SortUp","value":"Sortér op"},"SortZtoA":{"id":"SortZtoA","value":"Sortér faldende"},"Spanish":{"id":"Spanish","value":"Spansk"},"SplitterCollapseButton":{"id":"SplitterCollapseButton","value":"Skjul opdeling"},"SplitterDragHandle":{"id":"SplitterDragHandle","value":"Træk for at justere"},"StartsWith":{"id":"StartsWith","value":"Starter med"},"Status":{"id":"Status","value":"Status"},"StepsCompleted":{"id":"StepsCompleted","value":"{0} af {1} trin fuldført"},"StrikeThrough":{"id":"StrikeThrough","value":"Gennemstreget"},"String":{"id":"String","value":"Streng"},"Strings":{"id":"Strings","value":"Strenge"},"Subject":{"id":"Subject","value":"Emne"},"Submit":{"id":"Submit","value":"Send"},"Subscript":{"id":"Subscript","value":"Sænket skrift"},"Subtle":{"id":"Subtle","value":"Diskret"},"Superscript":{"id":"Superscript","value":"Hævet skrift"},"Swedish":{"id":"Swedish","value":"Svensk"},"Tabs":{"id":"Tabs","value":"Faner..."},"Tack":{"id":"Tack","value":"Nål"},"Tagalog":{"id":"Tagalog","value":"Tagalog"},"Tall":{"id":"Tall","value":"Høj"},"Target":{"id":"Target","value":"Destination"},"TeamEvent":{"id":"TeamEvent","value":"Teambegivenhed"},"TestLocaleDefaults":{"id":"TestLocaleDefaults","value":"Test landestandarder"},"TextBtnCancel":{"id":"TextBtnCancel","value":"Annuller overførsel af denne fil"},"TextBtnCloseError":{"id":"TextBtnCloseError","value":"Luk denne fejl"},"TextBtnRemove":{"id":"TextBtnRemove","value":"Luk denne fejl"},"TextColor":{"id":"TextColor","value":"Tekstfarve"},"TextDropArea":{"id":"DropArea","value":"Træk og slip de filer, der skal overføres"},"TextDropAreaWithBrowse":{"id":"TextDropAreaWithBrowse","value":"Træk og slip, eller <span class='hyperlink'>vælg filer</span>, der skal overføres"},"Thai":{"id":"Thai","value":"Thailandsk"},"Theme":{"id":"Theme","value":"Tema"},"ThousandsAbbrev":{"id":"ThousandsAbbrev","value":"{0}k"},"Time":{"id":"Time","value":"Tid"},"TimepickerPopup":{"id":"TimepickerPopup","value":"Tidsvælger-vindue"},"TimepickerTriggerButton":{"id":"TimepickerTriggerButton","value":"Klik for at åbne tidsvælgeren"},"Timer":{"id":"Timer","value":"Timer"},"To":{"id":"To","value":"Til"},"Today":{"id":"Today","value":"I dag"},"ToggleBold":{"id":"ToggleBold","value":"Slå fed tekst til/fra"},"ToggleH3":{"id":"ToggleH3","value":"Slå overskrift 3 til/fra"},"ToggleH4":{"id":"ToggleH4","value":"Slå overskrift 4 til/fra"},"ToggleItalic":{"id":"ToggleItalic","value":"Slå kursiv tekst til/fra"},"ToggleUnderline":{"id":"ToggleUnderline","value":"Slå understreget tekst til/fra"},"Toolbar":{"id":"Toolbar","value":"Værktøjslinje"},"TopAlign":{"id":"TopAlign","value":"Juster øverst"},"Total":{"id":"Total","value":"Total"},"Totals":{"id":"Totals","value":"Totaler"},"TreeCollapse":{"id":"TreeCollapse","value":"Skjul træ"},"TreeExpand":{"id":"TreeExpand","value":"Udvid træ"},"TrillionsAbbrev":{"id":"TrillionsAbbrev","value":"{0}T"},"Turkish":{"id":"Turkish","value":"Tyrkisk"},"Turquoise":{"id":"Turquoise","value":"Turkis"},"Type":{"id":"Type","value":"Type"},"TypeToFilter":{"id":"TypeToFilter","value":"Indtast for at filtrere"},"Ukrainian":{"id":"Ukrainian","value":"Ukrainsk"},"UnavailableDate":{"id":"UnavailableDate","value":"Utilgængelig dato"},"Underline":{"id":"Underline","value":"Understreget"},"Undo":{"id":"Undo","value":"Fortryd"},"Unlocked":{"id":"Unlocked","value":"Ulåst"},"UnorderedList":{"id":"UnorderedList","value":"Indsæt/Fjern punktopstilling"},"Unsupported":{"id":"Unsupported","value":"Dette indhold er ikke tilgængeligt, fordi det bruger funktioner, som ikke understøttes i den aktuelle browserversion."},"Up":{"id":"Up","value":"Op"},"UpComing":{"id":"UpComing","value":"Kommende"},"UpComingEvents":{"id":"UpComingEvents","value":"Kommende begivenheder"},"UpComingTimeOff":{"id":"UpComingTimeOff","value":"Kommende fritid"},"UpliftDarkTheme":{"id":"UpliftDarkTheme","value":"Uplift Mørk"},"UpliftHighContrastTheme":{"id":"UpliftHighContrastTheme","value":"Uplift Høj kontrast"},"UpliftLightTheme":{"id":"UpliftLightTheme","value":"Uplift Lys"},"Upload":{"id":"Upload","value":"Overfør"},"Url":{"id":"Url","value":"Webadresse"},"UseArrow":{"id":"UseArrow","value":". Brug piletaster til at vælge."},"UseEnter":{"id":"UseEnter","value":". Brug Enter eller pil ned til at slå op."},"User":{"id":"User","value":"Bruger"},"UserProfile":{"id":"UserProfile","value":"Brugerprofil"},"Variant":{"id":"Variant","value":"Variant"},"Version":{"id":"Version","value":"IDS-version"},"Versions":{"id":"Versions","value":"Versioner"},"VerticalMiddleAlign":{"id":"VerticalMiddleAlign","value":"Centrer lodret"},"Vibrant":{"id":"Vibrant","value":"Levende"},"Vietnamese":{"id":"Vietnamese","value":"Vietnamesisk"},"ViewSource":{"id":"ViewSource","value":"Vis kilde"},"ViewVisual":{"id":"ViewVisual","value":"Vis visuel"},"Week":{"id":"Week","value":"Uge"},"WeekNumber":{"id":"WeekNumber","value":"U#"},"Year":{"id":"Year","value":"År"},"Yes":{"id":"Yes","value":"Ja"}}